odoo/addons/account_tax_rounding_method/README.rst
odoo/addons/account_tax_rounding_method/__init__.py
odoo/addons/account_tax_rounding_method/__manifest__.py
odoo/addons/account_tax_rounding_method/i18n/account_tax_rounding_method.pot
odoo/addons/account_tax_rounding_method/i18n/ja.po
odoo/addons/account_tax_rounding_method/models/__init__.py
odoo/addons/account_tax_rounding_method/models/account_tax.py
odoo/addons/account_tax_rounding_method/models/res_company.py
odoo/addons/account_tax_rounding_method/models/res_config_settings.py
odoo/addons/account_tax_rounding_method/models/res_currency.py
odoo/addons/account_tax_rounding_method/models/res_partner.py
odoo/addons/account_tax_rounding_method/readme/CONFIGURE.md
odoo/addons/account_tax_rounding_method/readme/CONTEXT.md
odoo/addons/account_tax_rounding_method/readme/CONTRIBUTORS.md
odoo/addons/account_tax_rounding_method/readme/DESCRIPTION.md
odoo/addons/account_tax_rounding_method/readme/USAGE.md
odoo/addons/account_tax_rounding_method/static/description/icon.png
odoo/addons/account_tax_rounding_method/static/description/index.html
odoo/addons/account_tax_rounding_method/tests/__init__.py
odoo/addons/account_tax_rounding_method/tests/test_account_tax_round_down.py
odoo/addons/account_tax_rounding_method/views/res_config_settings_views.xml
odoo/addons/account_tax_rounding_method/views/res_partner_views.xml
odoo_addon_account_tax_rounding_method-18.0.1.0.0.3.dist-info/METADATA
odoo_addon_account_tax_rounding_method-18.0.1.0.0.3.dist-info/WHEEL
odoo_addon_account_tax_rounding_method-18.0.1.0.0.3.dist-info/top_level.txt
odoo_addon_account_tax_rounding_method-18.0.1.0.0.3.dist-info/RECORD
